Metadata-Version: 2.1
Name: flask-session-azure
Version: 0.4.3
Summary: Flask Session using Azure Table Storage or CosmosDB table API
Home-page: https://github.com/claasd/FlaskAzureTableSession
Author: Claas Diederichs
Author-email: 
License: MIT
Platform: UNKNOWN
Classifier: Framework :: Flask
Classifier: Programming Language :: Python :: 3.6
Classifier: Programming Language :: Python :: 3.7
Classifier: Programming Language :: Python :: 3.8
Classifier: License :: OSI Approved :: MIT License
Classifier: Operating System :: OS Independent
Requires-Python: >=3.6
Requires-Dist: azure-cosmosdb-table (~=1.0.6)
Requires-Dist: pycryptodomex (~=3.9.7)
Requires-Dist: flask
